notable_moments-0.2.0.dist-info/METADATA
notable_moments-0.2.0.dist-info/WHEEL
notable_moments-0.2.0.dist-info/entry_points.txt
notable_moments/__init__.py
notable_moments/graph.py
notable_moments/msg.py
notable_moments/nm.py
notable_moments-0.2.0.dist-info/RECORD
