Metadata-Version: 2.1
Name: notable_moments
Version: 0.2.0
Summary: Get notable timestamps from a YT VOD via livestream chat
Author-Email: hemakodaa <hemakodaa@gmail.com>
License: MIT
Requires-Python: >=3.11
Requires-Dist: chat-downloader>=0.2.8
Requires-Dist: numpy>=2.2.1
Requires-Dist: matplotlib>=3.10.0
Requires-Dist: bs4>=0.0.2
Requires-Dist: requests>=2.32.3
Requires-Dist: lxml>=5.3.0
